easyqueue/__init__.py
easyqueue/async.py
easyqueue/exceptions.py
easyqueue/queue.py
easyqueue-1.0.0.dist-info/METADATA
easyqueue-1.0.0.dist-info/RECORD
easyqueue-1.0.0.dist-info/WHEEL
easyqueue-1.0.0.dist-info/top_level.txt
tests/__init__.py
tests/test_async_queue.py
tests/test_base_json_queue.py
tests/test_queue.py
tests/test_testutils.py
tests/utils.py
